{
  "schemaId": "atm.taskTransition.v1",
  "specVersion": "0.1.0",
  "transitionId": "2026-07-16T12-46-00-115Z-import-07798229e0f6",
  "taskId": "TASK-RFT-0090",
  "action": "import",
  "actorId": null,
  "sessionId": null,
  "fromStatus": null,
  "toStatus": "planned",
  "taskPath": ".atm/history/tasks/TASK-RFT-0090.json",
  "taskSha256": "sha256:8e265fb2e6bb2058bf188645563af162d9d93026ee2b19065ddf1bb694d895e5",
  "createdAt": "2026-07-16T12:46:00.115Z",
  "command": "node atm.mjs tasks import"
}
