{
  "schemaId": "atm.taskTransition.v1",
  "specVersion": "0.1.0",
  "transitionId": "2026-05-25T14-29-21-587Z-reserve-01c6159a5e87",
  "taskId": "TASK-ASA-0005",
  "action": "reserve",
  "actorId": "opus47-asa-runner",
  "fromStatus": "planned",
  "toStatus": "reserved",
  "taskPath": ".atm/history/tasks/TASK-ASA-0005.json",
  "taskSha256": "sha256:04bf3e2efd8f4cb4132d50be49ee4b0e0bafd4c728d112a325253f3855fd907b",
  "createdAt": "2026-05-25T14:29:21.587Z",
  "command": "node atm.mjs tasks reserve"
}
