{
  "schemaId": "atm.taskTransition.v1",
  "specVersion": "0.1.0",
  "transitionId": "2026-06-14T10-20-39-991Z-claim-c78530b3a391",
  "taskId": "TASK-CID-0088",
  "action": "claim",
  "actorId": "captain",
  "sessionId": "session-20260614102039-captain-TASK-CID-0088-24255f3c98",
  "fromStatus": "ready",
  "toStatus": "running",
  "taskPath": ".atm/history/tasks/TASK-CID-0088.json",
  "taskSha256": "sha256:cd2171b81e30ed49202a4094e91abef708cf2ce69ff90b079533f9057677a188",
  "createdAt": "2026-06-14T10:20:39.991Z",
  "command": "node atm.mjs tasks claim"
}
