{
  "schemaVersion": "atm.workItem.v0.2",
  "workItemId": "TASK-GIT-0005",
  "title": "Pre-push hook installer",
  "status": "done",
  "milestone": "G2",
  "dependencies": [
    "TASK-GIT-0004"
  ],
  "acceptance": [
    "Hook installer writes a minimal, reviewable hook.",
    "Hook verifier confirms the hook points at the current ATM entry point.",
    "Uninstall restores the previous hook or reports that no ATM hook was installed.",
    "Hook output stays short and points to the full evidence report on failure."
  ],
  "deliverables": [
    "Install, verify, and uninstall flow for the ATM pre-push hook.",
    "Hook body that delegates to the CLI instead of embedding broker logic.",
    "Clear instructions for manual hook installation."
  ],
  "scopePaths": [
    "packages/cli/src/commands/integration.ts",
    "packages/cli/src/commands/git.ts",
    "integrations/**",
    "tests/cli/**"
  ],
  "validators": [
    "npm run typecheck",
    "npm run validate:cli",
    "git diff --check"
  ],
  "planningRepo": "3KLife",
  "targetRepo": "AI-Atomic-Framework",
  "closureAuthority": "target_repo",
  "planningReadOnlyPaths": [],
  "planningMirrorPaths": [],
  "outOfScope": [
    "No global Git config mutation without explicit operator command."
  ],
  "nonGoals": [
    "No attempt to prevent deliberate `--no-verify` bypass."
  ],
  "evidenceRequired": "command-backed",
  "rollbackStrategy": null,
  "rollbackNotes": null,
  "atomizationImpact": {
    "ownerAtomOrMap": "atm.git-pre-push-hook",
    "atomCid": null,
    "mapUpdates": []
  },
  "legacyImportAliases": {},
  "importDiagnostics": [],
  "tags": [],
  "notes": null,
  "source": {
    "planPath": "git-boundary-admission/tasks/TASK-GIT-0005-pre-push-hook-installer.task.md",
    "sectionTitle": "TASK-GIT-0005",
    "headingLine": 35,
    "hash": "3a4f609aee1e104c"
  },
  "importedAt": "2026-06-23T04:08:47.313Z",
  "lastTransitionId": "2026-06-23T05-20-33-734Z-close-b75fbc03fdf0",
  "lastTransitionAt": "2026-06-23T05:20:33.734Z",
  "ledgerContractVersion": "task-ledger/v1",
  "owner": "codex-main",
  "reservedAt": "2026-06-23T05:06:21.255Z",
  "promotedAt": "2026-06-23T05:06:21.258Z",
  "claim": {
    "actorId": "codex-main",
    "leaseId": "lease-09bbd50617c8",
    "claimedAt": "2026-06-23T05:06:21.260Z",
    "heartbeatAt": "2026-06-23T05:20:33.732Z",
    "ttlSeconds": 1800,
    "files": [
      ".atm/history/tasks/TASK-GIT-0005.json",
      "integrations/**",
      "packages/cli/src/commands/git.ts",
      "packages/cli/src/commands/integration.ts",
      "tests/cli/**"
    ],
    "state": "released",
    "reason": "closed"
  },
  "startedAt": "2026-06-23T05:06:21.260Z",
  "startedByActor": "codex-main",
  "startedBySessionId": "session-20260623050621-codex-main-TASK-GIT-0005-10d46dcc64",
  "taskDirectionLock": {
    "schemaId": "atm.taskDirectionLock.v1",
    "specVersion": "0.1.0",
    "taskId": "TASK-GIT-0005",
    "batchId": "batch-f47cb3485465",
    "scopeKey": "tasks-023ae6299ffc",
    "queueId": "queue-22c39256af85f43e",
    "queueIndex": 4,
    "allowedFiles": [
      ".atm/history/evidence/TASK-GIT-0005.*",
      ".atm/history/task-events/TASK-GIT-0005/**",
      ".atm/history/tasks/TASK-GIT-0005.json",
      "integrations/**",
      "packages/cli/src/commands/git.ts",
      "packages/cli/src/commands/integration.ts",
      "tests/cli/**"
    ],
    "planningReadOnlyPaths": [],
    "planningMirrorPaths": [],
    "allowPlanningMirror": false,
    "promptHash": "11daed933f5141f1a8c745e4455952fe09f5c3d50139098a5f8686d2d7eef934",
    "actorId": "codex-main",
    "createdAt": "2026-06-23T05:06:21.689Z",
    "status": "active"
  },
  "closedAt": "2026-06-23T05:20:33.732Z",
  "closedByActor": "codex-main",
  "closedBySessionId": "session-20260623050621-codex-main-TASK-GIT-0005-10d46dcc64",
  "closurePacket": ".atm/history/evidence/TASK-GIT-0005.closure-packet.json"
}
