{
  "schemaVersion": "atm.workItem.v0.2",
  "workItemId": "TASK-AAO-0097",
  "title": "tasks.ts wave 3-B file-I/O helpers split",
  "status": "done",
  "milestone": null,
  "dependencies": [],
  "acceptance": [],
  "deliverables": [
    "packages/cli/src/commands/tasks.ts",
    "packages/cli/src/commands/tasks/task-file-io-helpers.ts",
    "tests/unit/task-file-io-helpers.unit.test.ts",
    "atomic_workbench/atomization-coverage/path-to-atom-map.json"
  ],
  "tags": [],
  "notes": "- 2026-05-30 | 狀態: in-progress | 驗證: pending | 變更: 開卡完成，準備 Phase 1 移出實作 | 阻塞: 無",
  "source": {
    "planPath": "../3KLife/docs/ai_atomic_framework/atm-agent-first-operability/tasks/TASK-AAO-0097-tasks-wave3b-file-io-helpers-split.task.md",
    "sectionTitle": "tasks.ts wave 3-B file-I/O helpers split",
    "headingLine": 19,
    "hash": "9d80b3f9af4f8cd1"
  },
  "importedAt": "2026-05-30T12:52:42.710Z",
  "lastTransitionId": "2026-05-30T12-57-20-286Z-close-d11b5b7d3e76",
  "lastTransitionAt": "2026-05-30T12:57:20.286Z",
  "ledgerContractVersion": "task-ledger/v1",
  "owner": "Antigravity",
  "reservedAt": "2026-05-30T12:52:59.505Z",
  "promotedAt": "2026-05-30T12:52:59.507Z",
  "claim": {
    "actorId": "Antigravity",
    "leaseId": "lease-1f595c8003b3",
    "claimedAt": "2026-05-30T12:52:59.509Z",
    "heartbeatAt": "2026-05-30T12:57:20.286Z",
    "ttlSeconds": 1800,
    "files": [
      ".atm/history/tasks/TASK-AAO-0097.json",
      "atm.mjs",
      "atomic_workbench/atomization-coverage/path-to-atom-map.json",
      "atomic_workbench/atomization-coverage/path-to-atom-map.json (新 atom 登記",
      "package.json",
      "packages/cli/src/commands/tasks.ts",
      "packages/cli/src/commands/tasks.ts (移出 7 函數、留 re-export",
      "packages/cli/src/commands/tasks/task-file-io-helpers.ts",
      "packages/cli/src/commands/tasks/task-file-io-helpers.ts (新建",
      "scripts/validate-cli.ts",
      "scripts/validate-git-head-evidence.ts",
      "tests/unit/task-file-io-helpers.unit.test.ts",
      "tests/unit/task-file-io-helpers.unit.test.ts (新建測試"
    ],
    "state": "released",
    "reason": "closed"
  },
  "startedAt": "2026-05-30T12:52:59.509Z",
  "startedByActor": "Antigravity",
  "startedBySessionId": "session-20260530125259-Antigravity-TASK-AAO-0097-6d4d4a5457",
  "taskDirectionLock": {
    "schemaId": "atm.taskDirectionLock.v1",
    "specVersion": "0.1.0",
    "taskId": "TASK-AAO-0097",
    "batchId": null,
    "scopeKey": null,
    "queueId": null,
    "queueIndex": null,
    "allowedFiles": [
      ".atm/history/evidence/TASK-AAO-0097.*",
      ".atm/history/task-events/TASK-AAO-0097/**",
      ".atm/history/tasks/TASK-AAO-0097.json",
      "atm.mjs",
      "atomic_workbench/atomization-coverage/path-to-atom-map.json",
      "package.json",
      "packages/cli/src/commands/tasks.ts",
      "packages/cli/src/commands/tasks/task-file-io-helpers.ts",
      "scripts/validate-cli.ts",
      "scripts/validate-git-head-evidence.ts",
      "tests/unit/task-file-io-helpers.unit.test.ts"
    ],
    "planningReadOnlyPaths": [],
    "planningMirrorPaths": [],
    "allowPlanningMirror": false,
    "promptHash": "5d287d2633c6f5f03d1e41a9da686f83f0aa46ec24b07557cef0bccdbb0a4987",
    "actorId": "Antigravity",
    "createdAt": "2026-05-30T12:52:59.519Z",
    "status": "active"
  },
  "closurePacket": ".atm/history/evidence/TASK-AAO-0097.closure-packet.json",
  "closedAt": "2026-05-30T12:57:20.286Z",
  "closedByActor": "Antigravity",
  "closedBySessionId": "session-20260530125259-Antigravity-TASK-AAO-0097-6d4d4a5457"
}
