{
  "schemaId": "atm.taskTransition.v1",
  "specVersion": "0.1.0",
  "transitionId": "2026-06-14T04-03-47-800Z-reserve-24fc6e2cdf91",
  "taskId": "TASK-CID-0080",
  "action": "reserve",
  "actorId": "captain",
  "sessionId": null,
  "fromStatus": "planned",
  "toStatus": "reserved",
  "taskPath": ".atm/history/tasks/TASK-CID-0080.json",
  "taskSha256": "sha256:2dd1a499ccfca74db979cf53ed925e368a73391dc9ba0575603c90c7ea7382dc",
  "createdAt": "2026-06-14T04:03:47.800Z",
  "command": "node atm.mjs tasks reserve"
}
