{
  "schemaId": "atm.taskTransition.v1",
  "specVersion": "0.1.0",
  "transitionId": "2026-06-19T00-40-48-794Z-import-c75a86235abf",
  "taskId": "TASK-AAO-0123",
  "action": "import",
  "actorId": null,
  "sessionId": null,
  "fromStatus": "done",
  "toStatus": "open",
  "taskPath": ".atm/history/tasks/TASK-AAO-0123.json",
  "taskSha256": "sha256:656e68682db5dfd86fa58341ce159cf3435ee790bf1e460a13641922ba0b902e",
  "createdAt": "2026-06-19T00:40:48.794Z",
  "command": "node atm.mjs tasks import"
}
