{
  "schemaId": "atm.taskTransition.v1",
  "specVersion": "0.1.0",
  "transitionId": "2026-06-04T07-41-09-680Z-import-676e9b6d19da",
  "taskId": "TASK-AAO-0123",
  "action": "import",
  "actorId": null,
  "sessionId": null,
  "fromStatus": null,
  "toStatus": "open",
  "taskPath": ".atm/history/tasks/TASK-AAO-0123.json",
  "taskSha256": "sha256:2766255dd2f6ffa494808a04c8cd72ea3a55faf42de22f822933f60861e896b0",
  "createdAt": "2026-06-04T07:41:09.680Z",
  "command": "node atm.mjs tasks import"
}
