{
  "schemaId": "atm.taskTransition.v1",
  "specVersion": "0.1.0",
  "transitionId": "2026-05-29T17-13-32-705Z-import-b7d32d70254e",
  "taskId": "TASK-AAO-0080",
  "action": "import",
  "actorId": null,
  "sessionId": null,
  "fromStatus": null,
  "toStatus": "planned",
  "taskPath": ".atm/history/tasks/TASK-AAO-0080.json",
  "taskSha256": "sha256:2bf495bb0ba74dfab3e1647c04b36a63c838ede7ee4b6e3071e26ce740f02d79",
  "createdAt": "2026-05-29T17:13:32.705Z",
  "command": "node atm.mjs tasks import"
}
