{
  "schemaId": "atm.taskTransition.v1",
  "specVersion": "0.1.0",
  "transitionId": "2026-06-17T12-10-33-104Z-promote-e8c0f1352007",
  "taskId": "TASK-MAO-0052",
  "action": "promote",
  "actorId": "cursor-composer-2.5",
  "sessionId": null,
  "fromStatus": "reserved",
  "toStatus": "ready",
  "taskPath": ".atm/history/tasks/TASK-MAO-0052.json",
  "taskSha256": "sha256:3e40823226f4bbf44522620000a8e255d3d0e3d4d62c5fbec8f8d7a947eeca0f",
  "createdAt": "2026-06-17T12:10:33.104Z",
  "command": "node atm.mjs tasks promote"
}
