{
  "schemaId": "atm.taskTransition.v1",
  "specVersion": "0.1.0",
  "transitionId": "2026-05-29T07-56-38-184Z-reserve-89ef8e6bb9ed",
  "taskId": "TASK-AAO-0074",
  "action": "reserve",
  "actorId": "copilot",
  "sessionId": null,
  "fromStatus": "open",
  "toStatus": "reserved",
  "taskPath": ".atm/history/tasks/TASK-AAO-0074.json",
  "taskSha256": "sha256:01710f058f8ca3be869d8394918026511a568ca93770110c40e1fcf92a108488",
  "createdAt": "2026-05-29T07:56:38.184Z",
  "command": "node atm.mjs tasks reserve"
}
