{
  "schemaId": "atm.taskTransition.v1",
  "specVersion": "0.1.0",
  "transitionId": "2026-07-07T01-58-14-152Z-import-fa41b3705889",
  "taskId": "TASK-RFT-0016",
  "action": "import",
  "actorId": null,
  "sessionId": null,
  "fromStatus": null,
  "toStatus": "open",
  "taskPath": ".atm/history/tasks/TASK-RFT-0016.json",
  "taskSha256": "sha256:10c35c1a0ee525233c26644be2da5ad3bc25a0898529bf357a43a3619a47ba6d",
  "createdAt": "2026-07-07T01:58:14.152Z",
  "command": "node atm.mjs tasks import"
}
